porsline/__init__.py
porsline/client.py
porsline/form.py
porsline/jalali_to_gregorian.py
porsline_sdk-0.2.2.dist-info/licenses/LICENSE
porsline_sdk-0.2.2.dist-info/METADATA
porsline_sdk-0.2.2.dist-info/WHEEL
porsline_sdk-0.2.2.dist-info/top_level.txt
porsline_sdk-0.2.2.dist-info/RECORD
