Metadata-Version: 2.4
Name: porsline-sdk
Version: 0.2.2
Summary: A lightweight SDK for interacting with Porsline forms and responses
Author-email: Matin Khosravi <matinkhosravi97@gmail.com>
License-Expression: MIT
Project-URL: Homepage, https://github.com/matinkhosravi/porsline-sdk
Requires-Python: >=3.7
License-File: LICENSE
Requires-Dist: requests
Requires-Dist: jdatetime
Dynamic: license-file
